{
    "landmarkList": [
        {
            "m_name": "hospital_receiver1_初始位置",
            "m_label": "",
            "m_data": [
                -111.71833038330078,
                0.04795384407043457,
                -52.003150939941409,
                140.0
            ]
        },
        {
            "m_name": "hospital_receiver2_初始位置",
            "m_label": "",
            "m_data": [
                -112.63162994384766,
                0.04795384407043457,
                -52.0166130065918,
                200.0
            ]
        },
        {
            "m_name": "hospital_receiver3_初始位置",
            "m_label": "",
            "m_data": [
                -113.19261169433594,
                0.04795386642217636,
                -51.1138916015625,
                -80.0
            ]
        },
        {
            "m_name": "hospital_receiver4_初始位置",
            "m_label": "",
            "m_data": [
                -112.45999908447266,
                0.05000000074505806,
                -50.43000030517578,
                -10.0
            ]
        },
        {
            "m_name": "hospital_stuff_交谈",
            "m_label": "",
            "m_data": [
                -106.5,
                0.029999999329447748,
                -49.060001373291019,
                -50.0
            ]
        },
        {
            "m_name": "hospital_stuff1_初始位置",
            "m_label": "",
            "m_data": [
                -108.64013671875,
                0.03497894108295441,
                -48.71173858642578,
                0.0
            ]
        },
        {
            "m_name": "hospital_stuff2_初始位置",
            "m_label": "",
            "m_data": [
                -107.48966217041016,
                0.03497898578643799,
                -48.69590377807617,
                0.0
            ]
        },
        {
            "m_name": "hospital_stuff2_交谈",
            "m_label": "",
            "m_data": [
                -107.48999786376953,
                0.029999999329447748,
                -48.70000076293945,
                140.0
            ]
        },
        {
            "m_name": "hospital_stuff3_初始位置",
            "m_label": "",
            "m_data": [
                -104.94270324707031,
                0.03497911989688873,
                -48.760650634765628,
                0.0
            ]
        },
        {
            "m_name": "hospital_stuff4_初始位置",
            "m_label": "",
            "m_data": [
                -103.8772964477539,
                0.034979164600372317,
                -48.785606384277347,
                0.0
            ]
        },
        {
            "m_name": "hospital_stuff5_初始位置",
            "m_label": "",
            "m_data": [
                -113.02999877929688,
                3.549999952316284,
                -50.36199951171875,
                0.0
            ]
        },
        {
            "m_name": "hospital_stuff6_初始位置",
            "m_label": "",
            "m_data": [
                -106.87999725341797,
                3.549999952316284,
                -52.09199905395508,
                0.0
            ]
        },
        {
            "m_name": "hospital_stuff7_初始位置",
            "m_label": "",
            "m_data": [
                -103.77999877929688,
                3.549999952316284,
                -49.119998931884769,
                90.0
            ]
        },
        {
            "m_name": "hospital_stuff8_初始位置",
            "m_label": "",
            "m_data": [
                -105.46115112304688,
                7.052520751953125,
                -51.43170928955078,
                180.0
            ]
        },
        {
            "m_name": "hospital_stuff8_看机器",
            "m_label": "",
            "m_data": [
                -103.2300033569336,
                7.050000190734863,
                -48.849998474121097,
                90.0
            ]
        },
        {
            "m_name": "hospital_stuff8_交谈",
            "m_label": "",
            "m_data": [
                -106.35652160644531,
                7.052519798278809,
                -50.95558547973633,
                -80.0
            ]
        },
        {
            "m_name": "hospital_patient1_看病",
            "m_label": "",
            "m_data": [
                -113.02999877929688,
                3.549999952316284,
                -49.08000183105469,
                180.0
            ]
        },
        {
            "m_name": "hospital_patient1_交谈",
            "m_label": "",
            "m_data": [
                -107.58999633789063,
                7.050000190734863,
                -51.13999938964844,
                70.0
            ]
        },
        {
            "m_name": "hospital_patient1_躺下",
            "m_label": "",
            "m_data": [
                -106.39027404785156,
                7.052520751953125,
                -49.00064468383789,
                0.0
            ]
        },
        {
            "m_name": "hospital_patient2_看病",
            "m_label": "",
            "m_data": [
                -108.2699966430664,
                3.559999942779541,
                -48.84199905395508,
                180.0
            ]
        },
        {
            "m_name": "hospital_patient3_看病",
            "m_label": "",
            "m_data": [
                -107.08000183105469,
                3.559999942779541,
                -48.821998596191409,
                180.0
            ]
        },
        {
            "m_name": "hospital_patient4_看病",
            "m_label": "",
            "m_data": [
                -102.36000061035156,
                3.549999952316284,
                -49.09700012207031,
                -90.0
            ]
        },
        {
            "m_name": "hospital_patient1_初始位置",
            "m_label": "",
            "m_data": [
                -117.89485168457031,
                -0.001999989151954651,
                -54.45763397216797,
                -90.0
            ]
        },
        {
            "m_name": "hospital_patient2_初始位置",
            "m_label": "",
            "m_data": [
                -119.70967864990235,
                -0.0020000040531158449,
                -50.67607879638672,
                -90.0
            ]
        },
        {
            "m_name": "hospital_patient3_初始位置",
            "m_label": "",
            "m_data": [
                -118.31695556640625,
                -0.001999989151954651,
                -49.26100158691406,
                -90.0
            ]
        },
        {
            "m_name": "hospital_patient4_初始位置",
            "m_label": "",
            "m_data": [
                -113.03421020507813,
                -0.001999989151954651,
                -46.864227294921878,
                -90.0
            ]
        },
        {
            "m_name": "hospital_patient1_前台",
            "m_label": "",
            "m_data": [
                -114.0494155883789,
                0.04795386642217636,
                -50.973873138427737,
                90.0
            ]
        },
        {
            "m_name": "hospital_patient2_前台",
            "m_label": "",
            "m_data": [
                -112.4000015258789,
                0.05000000074505806,
                -49.310001373291019,
                180.0
            ]
        },
        {
            "m_name": "hospital_patient3_前台",
            "m_label": "",
            "m_data": [
                -114.0999984741211,
                0.05000000074505806,
                -52.279998779296878,
                60.0
            ]
        },
        {
            "m_name": "hospital_patient4_前台",
            "m_label": "",
            "m_data": [
                -113.68000030517578,
                0.05000000074505806,
                -49.58000183105469,
                140.0
            ]
        }
    ]
}