{
    "landmarkList": [
        {
            "m_name": "tower_数据员1_初始位置",
            "m_label": "",
            "m_data": [
                -167.21258544921876,
                28.307680130004884,
                61.25977325439453,
                0.0
            ]
        },
        {
            "m_name": "tower_数据员1_记笔记",
            "m_label": "",
            "m_data": [
                -168.93447875976563,
                28.307680130004884,
                61.56615447998047,
                120.0
            ]
        },
        {
            "m_name": "tower_数据员2_初始位置",
            "m_label": "",
            "m_data": [
                -168.66000366210938,
                25.190000534057618,
                61.470001220703128,
                150.0
            ]
        },
        {
            "m_name": "tower_数据员3_初始位置",
            "m_label": "",
            "m_data": [
                -172.04165649414063,
                17.66827964782715,
                63.175289154052737,
                150.0
            ]
        },
        {
            "m_name": "tower_数据员3_笔记",
            "m_label": "",
            "m_data": [
                -173.5,
                17.670000076293947,
                61.59000015258789,
                100.0
            ]
        },
        {
            "m_name": "tower_数据员4_初始位置",
            "m_label": "",
            "m_data": [
                -173.02999877929688,
                14.050000190734864,
                62.459999084472659,
                125.0
            ]
        },
        {
            "m_name": "tower_数据员5_初始位置",
            "m_label": "",
            "m_data": [
                -172.92120361328126,
                10.292642593383789,
                62.3715705871582,
                125.0
            ]
        },
        {
            "m_name": "tower_客服1_初始位置",
            "m_label": "",
            "m_data": [
                -170.10000610351563,
                21.059999465942384,
                60.790000915527347,
                5.0
            ]
        },
        {
            "m_name": "tower_客服2_初始位置",
            "m_label": "",
            "m_data": [
                -171.3300018310547,
                21.059999465942384,
                61.06999969482422,
                5.0
            ]
        },
        {
            "m_name": "tower_客服3_初始位置",
            "m_label": "",
            "m_data": [
                -172.6300048828125,
                21.059999465942384,
                61.25,
                5.0
            ]
        }
    ]
}