{
    "landmarkList": [
        {
            "m_name": "办公点一",
            "m_label": "",
            "m_data": [
                -106.66000366210938,
                7.0,
                2.799999952316284,
                90.0
            ]
        },
        {
            "m_name": "办公点二",
            "m_label": "",
            "m_data": [
                -103.0,
                7.0,
                2.4000000953674318,
                180.0
            ]
        },
        {
            "m_name": "办公点三",
            "m_label": "",
            "m_data": [
                -100.97000122070313,
                7.0,
                2.4100000858306886,
                180.0
            ]
        },
        {
            "m_name": "受访点",
            "m_label": "",
            "m_data": [
                -103.80000305175781,
                7.0,
                5.0,
                -90.0
            ]
        },
        {
            "m_name": "采访点",
            "m_label": "",
            "m_data": [
                -105.0,
                7.0,
                5.0,
                90.0
            ]
        },
        {
            "m_name": "开会点一",
            "m_label": "",
            "m_data": [
                -106.48999786376953,
                3.5,
                2.0,
                90.0
            ]
        },
        {
            "m_name": "开会点二",
            "m_label": "",
            "m_data": [
                -105.30999755859375,
                3.5,
                2.9000000953674318,
                180.0
            ]
        },
        {
            "m_name": "开会点三",
            "m_label": "",
            "m_data": [
                -104.05999755859375,
                3.5,
                2.9000000953674318,
                180.0
            ]
        }
    ]
}